README.txt
setup.py
docs/HISTORY.txt
docs/INSTALL.txt
docs/LICENSE.GPL
docs/LICENSE.txt
plonetheme/__init__.py
plonetheme.colorfulworld.egg-info/PKG-INFO
plonetheme.colorfulworld.egg-info/SOURCES.txt
plonetheme.colorfulworld.egg-info/dependency_links.txt
plonetheme.colorfulworld.egg-info/entry_points.txt
plonetheme.colorfulworld.egg-info/namespace_packages.txt
plonetheme.colorfulworld.egg-info/not-zip-safe
plonetheme.colorfulworld.egg-info/requires.txt
plonetheme.colorfulworld.egg-info/top_level.txt
plonetheme/colorfulworld/__init__.py
plonetheme/colorfulworld/configure.zcml
plonetheme/colorfulworld/setuphandlers.py
plonetheme/colorfulworld/tests.py
plonetheme/colorfulworld/Extensions/Install.py
plonetheme/colorfulworld/Extensions/__init__.py
plonetheme/colorfulworld/browser/__init__.py
plonetheme/colorfulworld/browser/configure.zcml
plonetheme/colorfulworld/browser/interfaces.py
plonetheme/colorfulworld/browser/viewlets/__init__.py
plonetheme/colorfulworld/browser/viewlets/footer.pt
plonetheme/colorfulworld/browser/viewlets/searchbox.pt
plonetheme/colorfulworld/profiles/default/cssregistry.xml
plonetheme/colorfulworld/profiles/default/metadata.xml
plonetheme/colorfulworld/profiles/default/plonetheme.colorfulworld_various.txt
plonetheme/colorfulworld/profiles/default/skins.xml
plonetheme/colorfulworld/profiles/default/viewlets.xml
plonetheme/colorfulworld/profiles/uninstall/cssregistry.xml
plonetheme/colorfulworld/profiles/uninstall/skins.xml
plonetheme/colorfulworld/profiles/uninstall/viewlets.xml
plonetheme/colorfulworld/skins/colorfulworld_images/CONTENT.txt
plonetheme/colorfulworld/skins/colorfulworld_images/bg_h3.png
plonetheme/colorfulworld/skins/colorfulworld_images/bg_logo.png
plonetheme/colorfulworld/skins/colorfulworld_images/bg_menu.png
plonetheme/colorfulworld/skins/colorfulworld_images/bg_page.png
plonetheme/colorfulworld/skins/colorfulworld_images/search_ico.png
plonetheme/colorfulworld/skins/colorfulworld_styles/CONTENT.txt
plonetheme/colorfulworld/skins/colorfulworld_styles/colorfulworld.css