Metadata-Version: 1.0
Name: plonetheme.colorfulworld
Version: 1.0.1
Summary: An installable theme for Plone 4
Home-page: http://www.sixfeetup.com
Author: Six Feet Up, Inc.
Author-email: info@sixfeetup.com
License: GPL
Keywords: web zope plone theme
Platform: UNKNOWN
Classifier: Framework :: Plone
Classifier: Programming Language :: Python
